mockito/__init__.py
mockito/inorder.py
mockito/invocation.py
mockito/matchers.py
mockito/mock_registry.py
mockito/mocking.py
mockito/mockito.py
mockito/signature.py
mockito/spying.py
mockito/utils.py
mockito/verification.py
mockito-1.5.2.dist-info/METADATA
mockito-1.5.2.dist-info/WHEEL
mockito-1.5.2.dist-info/licenses/AUTHORS
mockito-1.5.2.dist-info/licenses/LICENSE
mockito-1.5.2.dist-info/RECORD
