Metadata-Version: 2.3
Name: mockito
Version: 1.5.2
Summary: Spying framework
Author-email: herr kaste <herr.kaste@gmail.com>
License: MIT
License-File: AUTHORS
License-File: LICENSE
Requires-Python: >=3.7
